curldrop/__init__.py
curldrop/app.py
curldrop/cli.py
curldrop/server.py
curldrop-1.0.5.dist-info/LICENSE.md
curldrop-1.0.5.dist-info/METADATA
curldrop-1.0.5.dist-info/WHEEL
curldrop-1.0.5.dist-info/entry_points.txt
curldrop-1.0.5.dist-info/top_level.txt
curldrop-1.0.5.dist-info/RECORD
