Metadata-Version: 2.1
Name: curldrop
Version: 1.0.5
Summary: UNKNOWN
Home-page: http://github.com/kennell/curldrop
Author: Kevin Kennell
Author-email: kevin@kennell.de
License: MIT
Platform: UNKNOWN
Requires-Dist: flask
Requires-Dist: click
Requires-Dist: gunicorn
Requires-Dist: six
